pyxesxxn
