Metadata-Version: 2.4
Name: pyxesxxn
Version: 1.0.0
Summary: PyXESXXN - Python for eXtended Energy System Analysis - Independent multi-carrier energy system modeling and optimization library
Home-page: https://github.com/pyxesxxn/pyxesxxn
Author: PyXESXXN Development Team
Author-email: PyXESXXN Development Team <support@pyxesxxn.org>
Maintainer-email: PyXESXXN Development Team <support@pyxesxxn.org>
License: Proprietary - Free for use, closed source
Project-URL: Homepage, https://github.com/pyxesxxn/pyxesxxn
Project-URL: Documentation, https://pyxesxxn.readthedocs.io
Project-URL: Repository, https://github.com/pyxesxxn/pyxesxxn
Project-URL: Issues, https://github.com/pyxesxxn/pyxesxxn/issues
Project-URL: Website, https://pyxesxxn.org
Keywords: energy,optimization,multi-carrier,power-systems,renewable-energy,energy-system,independent,closed-source,energy-hub,power-flow,reinforcement-learning,stochastic-optimization
Classifier: Development Status :: 5 - Production/Stable
Classifier: Intended Audience :: Science/Research
Classifier: Intended Audience :: Developers
Classifier: Topic :: Scientific/Engineering
Classifier: Topic :: Scientific/Engineering :: Physics
Classifier: Topic :: Software Development :: Libraries :: Python Modules
Classifier: Programming Language :: Python :: 3
Classifier: Programming Language :: Python :: 3.11
Classifier: Programming Language :: Python :: 3.12
Classifier: Programming Language :: Python :: 3.13
Classifier: Operating System :: OS Independent
Classifier: Natural Language :: English
Classifier: Natural Language :: Chinese (Simplified)
Classifier: Typing :: Typed
Classifier: License :: Other/Proprietary License
Requires-Python: >=3.11
Requires-Dist: numpy>=1.21
Requires-Dist: scipy>=1.7
Requires-Dist: pandas>=1.3
Requires-Dist: xarray>=0.20
Requires-Dist: matplotlib>=3.5
Requires-Dist: plotly>=5.0
Requires-Dist: seaborn>=0.11
Requires-Dist: geopandas>=0.10
Requires-Dist: shapely>=1.8
Requires-Dist: networkx>=2.6
Requires-Dist: deprecation>=2.1
Requires-Dist: highspy>=1.5
Requires-Dist: scikit-learn>=1.0
Requires-Dist: pyyaml>=5.4
Requires-Dist: imbalanced-learn>=0.8
Requires-Dist: feature-engine>=1.2
Requires-Dist: dash>=2.0
Requires-Dist: dash-bootstrap-components>=1.0
Requires-Dist: numba>=0.55
Requires-Dist: joblib>=1.1
Requires-Dist: torch>=1.11.0
Requires-Dist: gymnasium>=0.26.0
Provides-Extra: hdf5
Requires-Dist: tables>=3.7; extra == "hdf5"
Provides-Extra: excel
Requires-Dist: openpyxl>=3.0; extra == "excel"
Requires-Dist: python-calamine>=0.1; extra == "excel"
Provides-Extra: netcdf
Requires-Dist: netcdf4>=1.6; extra == "netcdf"
Provides-Extra: cloudpath
Requires-Dist: cloudpathlib>=0.6; extra == "cloudpath"
Provides-Extra: cartopy
Requires-Dist: cartopy>=0.21; extra == "cartopy"
Provides-Extra: geospatial
Requires-Dist: geopandas>=0.12; extra == "geospatial"
Requires-Dist: cartopy>=0.21; extra == "geospatial"
Requires-Dist: pyproj>=3.0; extra == "geospatial"
Provides-Extra: gurobi
Requires-Dist: gurobipy>=10.0; extra == "gurobi"
Provides-Extra: cplex
Requires-Dist: docplex>=2.22; extra == "cplex"
Provides-Extra: scip
Requires-Dist: pyscipopt>=4.0; extra == "scip"
Provides-Extra: pyomo
Requires-Dist: pyomo>=6.6.0; extra == "pyomo"
Requires-Dist: omlt>=0.5.0; extra == "pyomo"
Provides-Extra: interactive
Requires-Dist: plotly>=5.0; extra == "interactive"
Requires-Dist: dash>=2.0; extra == "interactive"
Requires-Dist: ipywidgets>=8.0; extra == "interactive"
Provides-Extra: webgl
Requires-Dist: pydeck>=0.8; extra == "webgl"
Provides-Extra: dev
Requires-Dist: pytest>=7.0; extra == "dev"
Requires-Dist: pytest-cov>=4.0; extra == "dev"
Requires-Dist: pytest-mpl>=0.15; extra == "dev"
Requires-Dist: coverage>=7.0; extra == "dev"
Requires-Dist: pytest-xdist>=3.0; extra == "dev"
Requires-Dist: hypothesis>=6.0; extra == "dev"
Requires-Dist: pre-commit>=3.0; extra == "dev"
Requires-Dist: ruff>=0.1; extra == "dev"
Requires-Dist: mypy>=1.0; extra == "dev"
Requires-Dist: black>=23.0; extra == "dev"
Requires-Dist: isort>=5.12; extra == "dev"
Requires-Dist: jupyter>=1.0; extra == "dev"
Requires-Dist: ipython>=8.0; extra == "dev"
Requires-Dist: typing-extensions>=4.5; extra == "dev"
Provides-Extra: docs
Requires-Dist: sphinx>=7.0; extra == "docs"
Requires-Dist: sphinx-rtd-theme>=1.3; extra == "docs"
Requires-Dist: sphinx-autodoc-typehints>=1.23; extra == "docs"
Requires-Dist: sphinx-copybutton>=0.5; extra == "docs"
Requires-Dist: sphinx-design>=0.4; extra == "docs"
Requires-Dist: myst-parser>=2.0; extra == "docs"
Requires-Dist: nbsphinx>=0.9; extra == "docs"
Requires-Dist: jupyter-sphinx>=0.4; extra == "docs"
Provides-Extra: full
Requires-Dist: pyxesxxn[cloudpath,cplex,excel,geospatial,gurobi,hdf5,interactive,netcdf,scip,webgl]; extra == "full"
Dynamic: author
Dynamic: home-page
Dynamic: requires-python
